odoo/addons/analytic_tag_dimension/README.rst
odoo/addons/analytic_tag_dimension/__init__.py
odoo/addons/analytic_tag_dimension/__manifest__.py
odoo/addons/analytic_tag_dimension/hooks.py
odoo/addons/analytic_tag_dimension/demo/analytic_demo.xml
odoo/addons/analytic_tag_dimension/i18n/analytic_tag_dimension.pot
odoo/addons/analytic_tag_dimension/i18n/ar.po
odoo/addons/analytic_tag_dimension/i18n/bs.po
odoo/addons/analytic_tag_dimension/i18n/ca.po
odoo/addons/analytic_tag_dimension/i18n/cs.po
odoo/addons/analytic_tag_dimension/i18n/cs_CZ.po
odoo/addons/analytic_tag_dimension/i18n/de.po
odoo/addons/analytic_tag_dimension/i18n/en_GB.po
odoo/addons/analytic_tag_dimension/i18n/es.po
odoo/addons/analytic_tag_dimension/i18n/es_CO.po
odoo/addons/analytic_tag_dimension/i18n/es_CR.po
odoo/addons/analytic_tag_dimension/i18n/es_EC.po
odoo/addons/analytic_tag_dimension/i18n/es_MX.po
odoo/addons/analytic_tag_dimension/i18n/et.po
odoo/addons/analytic_tag_dimension/i18n/fi.po
odoo/addons/analytic_tag_dimension/i18n/fr.po
odoo/addons/analytic_tag_dimension/i18n/fr_CH.po
odoo/addons/analytic_tag_dimension/i18n/hr.po
odoo/addons/analytic_tag_dimension/i18n/hr_HR.po
odoo/addons/analytic_tag_dimension/i18n/hu.po
odoo/addons/analytic_tag_dimension/i18n/it.po
odoo/addons/analytic_tag_dimension/i18n/ja.po
odoo/addons/analytic_tag_dimension/i18n/lt.po
odoo/addons/analytic_tag_dimension/i18n/mk.po
odoo/addons/analytic_tag_dimension/i18n/mn.po
odoo/addons/analytic_tag_dimension/i18n/nb.po
odoo/addons/analytic_tag_dimension/i18n/nl.po
odoo/addons/analytic_tag_dimension/i18n/nl_BE.po
odoo/addons/analytic_tag_dimension/i18n/nl_NL.po
odoo/addons/analytic_tag_dimension/i18n/pt.po
odoo/addons/analytic_tag_dimension/i18n/pt_BR.po
odoo/addons/analytic_tag_dimension/i18n/pt_PT.po
odoo/addons/analytic_tag_dimension/i18n/ro.po
odoo/addons/analytic_tag_dimension/i18n/ru.po
odoo/addons/analytic_tag_dimension/i18n/sl.po
odoo/addons/analytic_tag_dimension/i18n/sv.po
odoo_addon_analytic_tag_dimension-15.0.1.0.2.2.dist-info/METADATA
odoo_addon_analytic_tag_dimension-15.0.1.0.2.2.dist-info/WHEEL
odoo_addon_analytic_tag_dimension-15.0.1.0.2.2.dist-info/top_level.txt
odoo_addon_analytic_tag_dimension-15.0.1.0.2.2.dist-info/RECORD
