Metadata-Version: 2.1
Name: odoo-addon-analytic_tag_dimension
Version: 15.0.1.0.2.2
Summary: Group Analytic Entries by Dimensions
Home-page: https://github.com/OCA/account-analytic
Author: PESOL, Tecnativa, Odoo Community Association (OCA)
Author-email: support@odoo-community.org
License: AGPL-3
Classifier: Programming Language :: Python
Classifier: Framework :: Odoo
Classifier: Framework :: Odoo :: 15.0
Classifier: License :: OSI Approved :: GNU Affero General Public License v3
Classifier: Development Status :: 6 - Mature
Requires-Python: >=3.8
Requires-Dist: odoo <15.1dev,>=15.0a
